Workbook

Sheet Master Checklist
A1: CôBa's Daughter × Glossy — September 2026 Master Checklist
A2: Two events: Glossy Pop NYC gift bags (Sep 11, FIT) + Glossy Campus Game Day booth, UT Austin (Sep 12). All costs are estimates — confirm before ordering.
A3: LEGEND — blue text: editable inputs (qty, unit cost, owner, dates). Yellow fill: placeholder to confirm (Buyer/Finance/Glossy). Black: formulas, do not type over. Add rows in the spare section; Total column recalculates.
A5: Item | B5: Event | C5: Category | D5: Qty | E5: Unit Cost ($) | F5: Total ($) | G5: Cost Type | H5: Owner | I5: Source / Vendor | J5: Delivery Route | K5: Due | L5: Status | M5: Notes
A6: Miniset — current version (Plan B) | B6: NYC Pop | C6: Product | D6: 100 | E6: 7 | F6: =D6*E6 -> 700 | G6: Inventory COGS | H6: Head of Products | I6: Amazon AWD warehouse | J6: AWD removal → NYC helper address | K6: Aug 22 | L6: Not started | M6: Unit cost = placeholder COGS, Finance to confirm. Superseded if Plan A miniset lands in time.
A7: Aloe Gel full-size (Plan B, gift bags) | B7: NYC Pop | C7: Product | D7: 100 | E7: 8.5 | F7: =D7*E7 -> 850 | G7: Inventory COGS | H7: Head of Products | I7: Amazon AWD warehouse | J7: AWD removal → NYC helper address | K7: Aug 22 | L7: Not started | M7: Placeholder COGS. Pairs with current miniset under Plan B.
A8: NEW miniset w/ loofah scrub (Plan A) | B8: NYC Pop | C8: Product | D8: 100 | E8: 0 | F8: =D8*E8 -> 0 | G8: Inventory COGS | H8: Buyer team | I8: VN production | J8: Sea/air → NYC (gate: must land by Sep 4) | K8: Jul 24 gate | L8: Awaiting Buyer | M8: GATE: Buyer lead-time answer by Jul 24. If landed-by-Sep-4 impossible → execute Plan B rows above. Unit cost TBD.
A9: Aloe Gel full-size (game-day gifts) | B9: Game Day | C9: Product | D9: 50 | E9: 8.5 | F9: =D9*E9 -> 425 | G9: Inventory COGS | H9: Head of Products | I9: Amazon AWD warehouse | J9: AWD removal → Austin house | K9: Aug 29 | L9: Not started | M9: Post-and-tag reward, capped/day. Placeholder COGS.
A10: Canvas drawstring bag, logo 1-color print | B10: NYC Pop | C10: Packaging | D10: 110 | E10: 2.9 | F10: =D10*E10 -> 319 | G10: Cash | H10: Brand Director | I10: US promo supplier (4imprint / Totally Promotional) | J10: US ship → NYC helper | K10: Aug 28 | L10: Not started | M10: 100 bags + 10 spares. Get 2 quotes; US supplier only (no intl lead-time risk).
A11: Tissue paper + ribbon fillers | B11: NYC Pop | C11: Packaging | D11: 1 | E11: 40 | F11: =D11*E11 -> 40 | G11: Cash | H11: NYC helper | I11: Amazon US | J11: US ship → NYC helper | K11: Aug 28 | L11: Not started | M11: Brand-adjacent colors: cream / kraft.
A12: Voucher booklet (perforated, binder-style) | B12: NYC Pop | C12: Printing | D12: 100 | E12: 1.7 | F12: =D12*E12 -> 170 | G12: Cash | H12: Brand Director | I12: US print (Vistaprint / local NYC) | J12: US ship → NYC helper | K12: Aug 28 | L12: Not started | M12: Unique codes per booklet if possible → per-bag attribution.
A13: Brand book, compact print | B13: NYC Pop | C13: Printing | D13: 100 | E13: 1 | F13: =D13*E13 -> 100 | G13: Cash | H13: Brand Director | I13: US print OR handcarry (Sao & Eva) | J13: US ship or handcarry | K13: Sep 8 | L13: Not started | M13: Compare: US print vs VN print + handcarry. Handcarry saves cash but adds luggage.
A14: Fortune ticket cards (quẻ), 500 pcs | B14: Game Day | C14: Printing | D14: 1 | E14: 90 | F14: =D14*E14 -> 90 | G14: Cash | H14: Brand Director + Emma | I14: Austin print shop | J14: Local pickup (Emma) | K14: Sep 5 | L14: Not started | M14: Western 'lucky ticket' design; voucher QR on back. Includes ~30 fortune texts.
A15: Numbered fortune sticks (craft dowels + numbering) | B15: Game Day | C15: Printing | D15: 100 | E15: 0.4 | F15: =D15*E15 -> 40 | G15: Cash | H15: Emma | I15: Craft store Austin + DIY numbering | J15: Local (Emma) | K15: Sep 5 | L15: Not started | M15: Wood craft dowels; number stamp or burnt-orange dip ends.
A16: Easels for brand panels | B16: Game Day | C16: Booth & Ops | D16: 7 | E16: 15 | F16: =D16*E16 -> 105 | G16: Cash | H16: Emma | I16: Amazon US | J16: US ship → Austin house | K16: Sep 8 | L16: Not started | M16: Reusable for every future US event.
A17: Cooler + ice + sanitary supplies | B17: Game Day | C17: Booth & Ops | D17: 1 | E17: 80 | F17: =D17*E17 -> 80 | G17: Cash | H17: Emma | I17: HEB / local | J17: Local (Emma) | K17: Sep 11 | L17: Not started | M17: Chilled aloe demo + cold towels.
A18: Booth misc (linens, tape, batteries, signage stands) | B18: Game Day | C18: Booth & Ops | D18: 1 | E18: 50 | F18: =D18*E18 -> 50 | G18: Cash | H18: Emma | I18: Local | J18: Local (Emma) | K18: Sep 10 | L18: Not started
A19: NYC helper — assembly + delivery to FIT | B19: NYC Pop | C19: Labor | D19: 1 | E19: 220 | F19: =D19*E19 -> 220 | G19: Cash | H19: Brand Director | I19: TaskRabbit / referral (hire by Aug 15) | J19: — | K19: Sep 9–10 work | L19: Not hired | M19: 1 day assembly + drop at FIT per Glossy load-in instructions. Different person from Emma.
A20: Emma — Austin prep + event day | B20: Game Day | C20: Labor | D20: 1 | E20: 350 | F20: =D20*E20 -> 350 | G20: Cash | H20: Brand Director | I20: Rehire (May event) | J20: — | K20: Sep 10–12 work | L20: To confirm | M20: Prep day (sticks, cards, kit assembly) + full event day.
A21: Parcels & AWD removal fees → NYC | B21: NYC Pop | C21: Logistics | D21: 1 | E21: 100 | F21: =D21*E21 -> 100 | G21: Cash | H21: Head of Products | I21: Amazon AWD + UPS/USPS | J21: US only | K21: Aug 22–28 | L21: Not started | M21: No international shipping. Handcarry (Sao & Eva) covers small/premium items only.
A22: Austin local transport & stock moves | B22: Game Day | C22: Logistics | D22: 1 | E22: 50 | F22: =D22*E22 -> 50 | G22: Cash | H22: Emma | I22: — | J22: Local | K22: Sep 10–12 | L22: Not started | M22: Austin house → campus load-in.
A23: Creator gifting kits (existing merch) | B23: Game Day | C23: Booth & Ops | D23: 6 | E23: 0 | F23: =D23*E23 -> 0 | G23: Existing stock | H23: Brand Director | I23: Austin house stock (rattan bags, scarves, fans) | J23: Already in Austin | K23: Sep 11 | L23: Planned | M23: $0 cash — rattan bags ×6, scarves, fans, brand books from existing stock.
A24: Contingency reserve | B24: Both | C24: Contingency | D24: 1 | E24: 310 | F24: =D24*E24 -> 310 | G24: Cash | H24: Brand Director | I24: — | J24: — | K24: — | L24: Reserved | M24: ~8% buffer for quote overruns / reprints / extra bags.
F25: =IF(D25*E25=0,"",D25*E25)
F26: =IF(D26*E26=0,"",D26*E26)
F27: =IF(D27*E27=0,"",D27*E27)
F28: =IF(D28*E28=0,"",D28*E28)
F29: =IF(D29*E29=0,"",D29*E29)
F30: =IF(D30*E30=0,"",D30*E30)
F31: =IF(D31*E31=0,"",D31*E31)
F32: =IF(D32*E32=0,"",D32*E32)
F33: =IF(D33*E33=0,"",D33*E33)
F34: =IF(D34*E34=0,"",D34*E34)
A36: TOTAL (all rows incl. additions) | F36: =SUM(F6:F34) -> 3999

Sheet Budget $4K
A1: Budget Allocation — Total $4,000 (both events)
A2: Estimated pulls live from Master Checklist (SUMIFS by Category). Allocations in blue are the plan — edit to reallocate; Remaining shows headroom.
B4: TOTAL BUDGET | C4: 4000
A6: Category | B6: Allocated ($) | C6: Estimated ($, live) | D6: Remaining ($) | E6: % of budget
A7: Product | B7: 1975 | C7: =SUMIFS('Master Checklist'!$F$6:$F$34,'Master Checklist'!$C$6:$C$34,A7) -> 1975 | D7: =B7-C7 -> 0 | E7: =B7/$C$4 -> 0.49375
A8: Packaging | B8: 360 | C8: =SUMIFS('Master Checklist'!$F$6:$F$34,'Master Checklist'!$C$6:$C$34,A8) -> 359 | D8: =B8-C8 -> 1 | E8: =B8/$C$4 -> 0.09
A9: Printing | B9: 400 | C9: =SUMIFS('Master Checklist'!$F$6:$F$34,'Master Checklist'!$C$6:$C$34,A9) -> 400 | D9: =B9-C9 -> 0 | E9: =B9/$C$4 -> 0.1
A10: Labor | B10: 570 | C10: =SUMIFS('Master Checklist'!$F$6:$F$34,'Master Checklist'!$C$6:$C$34,A10) -> 570 | D10: =B10-C10 -> 0 | E10: =B10/$C$4 -> 0.1425
A11: Booth & Ops | B11: 235 | C11: =SUMIFS('Master Checklist'!$F$6:$F$34,'Master Checklist'!$C$6:$C$34,A11) -> 235 | D11: =B11-C11 -> 0 | E11: =B11/$C$4 -> 0.05875
A12: Logistics | B12: 150 | C12: =SUMIFS('Master Checklist'!$F$6:$F$34,'Master Checklist'!$C$6:$C$34,A12) -> 150 | D12: =B12-C12 -> 0 | E12: =B12/$C$4 -> 0.0375
A13: Contingency | B13: 310 | C13: =SUMIFS('Master Checklist'!$F$6:$F$34,'Master Checklist'!$C$6:$C$34,A13) -> 310 | D13: =B13-C13 -> 0 | E13: =B13/$C$4 -> 0.0775
A14: TOTAL | B14: =SUM(B7:B13) -> 4000 | C14: =SUM(C7:C13) -> 3999 | D14: =SUM(D7:D13) -> 1 | E14: =B14/$C$4 -> 1
A17: View: cash out-of-pocket vs inventory
A18: Cash out-of-pocket | C18: =SUMIFS('Master Checklist'!$F$6:$F$34,'Master Checklist'!$G$6:$G$34,"Cash") -> 2024
A19: Inventory COGS (from AWD stock) | C19: =SUMIFS('Master Checklist'!$F$6:$F$34,'Master Checklist'!$G$6:$G$34,"Inventory COGS") -> 1975
A20: Existing stock (zero cost) | C20: =SUMIFS('Master Checklist'!$F$6:$F$34,'Master Checklist'!$G$6:$G$34,"Existing stock") -> 0
A21: Note: if the BOD treats AWD product as inventory (not event cash), the cash ask is ~$2.0K of the $4.0K envelope.

Sheet Event Ops
A1: Event Operations — run-of-show & prep timeline
A3: PREP TIMELINE (both events)
A4: Week / Date | B4: Milestone | C4: Owner | D4: Detail
A5: W Jul 20 | B5: Buyer lead-time answer — new miniset w/ loofah (GATE) | C5: Buyer team | D5: Decides Plan A vs Plan B for NYC bags. Must land NYC by Sep 4 to qualify.
A6: W Jul 20 | B6: Confirm bag count with Glossy (NYC) + booth specs with Dylan (Austin) | C6: Brand Director | D6: Bag qty drives product order; ask Glossy for load-in instructions at FIT.
A7: W Jul 24 | B7: Buyer confirms silk scarf qty (Austin creator kits) | C7: Buyer team
A8: W Jul 27 | B8: Fortune texts written (~30) + ticket card design; voucher booklet design | C8: Brand Director | D8: Reuse brand templates; Western 'lucky ticket' layout.
A9: W Aug 3 | B9: Order: drawstring bags, voucher booklets; Klaviyo/Shopify codes (GLOSSYPOP / GAMEDAY tags) | C9: Brand Director | D9: Clone Endless Summer flow; unique codes if budget allows.
A10: W Aug 10 | B10: Hire NYC helper (by Aug 15); creators booked via Glossy roster | C10: Brand Director | D10: NYC helper ≠ Emma; brief with photo guide for assembly.
A11: W Aug 17 | B11: AWD removal orders placed (NYC 100+100, Austin 50) | C11: Head of Products | D11: Allow 1–2 weeks AWD processing + transit.
A12: W Aug 24 | B12: All NYC components at helper's address; test-assemble 1 bag, photo-approve | C12: NYC helper | D12: Checklist per bag: miniset (+aloe if Plan B), voucher booklet, brand book, tissue.
A13: W Sep 1 | B13: Austin print pickup; sticks numbered; Emma dry-run of fortune table | C13: Emma
A14: Sep 8–10 | B14: Sao & Eva arrive (handcarry: brand books/premium small items); NYC bags assembled Sep 9–10 | C14: All | D14: Handcarry = US-entry personal luggage only, no intl freight.
A15: Sep 10 | B15: NYC: bags delivered to FIT per Glossy instructions | C15: NYC helper | D15: Get signed receipt + photos for report.
A16: Sep 11 | B16: Glossy Pop NYC (FIT) — bags distributed by Glossy; team is in Austin | C16: Glossy | D16: No staffing needed on site.
A17: Sep 11 | B17: Austin booth load-in prep + Emma brief + kit assembly | C17: All | D17: Per Dylan's load-in window.
A18: Sep 12 | B18: GAME DAY — booth from College GameDay morning through 6:30 PM kickoff | C18: All | D18: Run-of-show below.
A19: Sep 13 | B19: Debrief; content offload; voucher redemption tracking begins (thru Sep 30) | C19: Brand Director
A21: GAME DAY RUN-OF-SHOW — Sep 12, UT Austin
A22: Time (CT) | B22: Station / Activity | C22: Who | D22: Notes
A23: 07:30–09:00 | B23: Load-in, booth build (panels, lanterns, fortune table, aloe cooler) | C23: All 4 | D23: Per Dylan's window; photos of build for content.
A24: 09:00–12:00 | B24: College GameDay crowd — fortune draws open; founder 'come with me' reel | C24: Emma (fortune) · Sao (content) | D24: Content check-in every hour.
A25: 12:00–15:00 | B25: Peak heat — chilled aloe demos + fans; creators visit booth | C25: Eva (aloe) · Sao (creators) | D25: Creators shoot at lantern corner; kits handed.
A26: 15:00–18:00 | B26: Golden hour — lantern photo corner peak; hourly scarf draw | C26: All | D26: Best light for UGC; announce draws to hold crowd.
A27: 18:00–18:30 | B27: Pre-kickoff push — last draws, aloe gifts for tagged posts | C27: All | D27: Cap check on aloe stock.
A28: 18:30+ | B28: Teardown OR stay through game per Dylan's schedule | C28: Emma + helper hands | D28: Inventory count → report.
A30: ROLES
A31: Person | B31: Role | C31: Where | D31: Notes
A32: Sao | B32: Founder face, creator hosting, content lead | C32: Austin | D32: Handcarry premium small items from VN.
A33: Eva | B33: Aloe station + ops support | C33: Austin | D33: Handcarry partner with Sao.
A34: Emma | B34: Fortune table, prep, logistics (Austin) | C34: Austin | D34: Rehired from May event.
A35: NYC helper (hire by Aug 15) | B35: Gift bag assembly + FIT delivery | C35: NYC | D35: Independent hire; photo-guided assembly brief.
A36: Dylan (Glossy) | B36: Booth PIC — specs, load-in, creator roster | C36: Glossy | D36: All booth design decisions confirmed with him.

Sheet Marketing Capture
A1: Marketing Capture Plan — make both events work online
A3: TRACKING SETUP (before Aug 15)
A4: Mechanism | B4: How | C4: Owner | D4: KPI
A5: Voucher codes — NYC | B5: Booklet code(s) scoped + tagged 'glossypop' in Shopify; unique per booklet if print allows | C5: Brand Director | D5: Redemptions by Sep 30
A6: Voucher QR — Game Day | B6: Ticket-card QR → Klaviyo signup → single-use 15–20% code tagged 'gameday' | C6: Brand Director | D6: 250–400 emails; redemptions
A7: UGC loop — Game Day | B7: Draw quẻ → photo at lantern corner → post IG + tag @cobasdaughter → Aloe Gel gift | C7: Emma enforces at booth | D7: 60–80 tagged posts/stories
A8: Hashtag & mentions | B8: #cobasdaughter monitored during Sep 11–14; reshare best to stories | C8: Brand team VN | D8: Mentions lift vs Aug baseline
A9: Amazon branded search | B9: Watch branded-search trend Sep 12–30 (May event precedent: +327% w/ SB) | C9: Head of Products | D9: Branded search lift
A11: CONTENT SHOT LIST — Game Day (owner: Sao)
A12: Asset | B12: Format | C12: When | D12: Destination
A13: Founder 'come with me to game day' reel | B13: IG reel 30–60s | C13: Morning → dusk arc | D13: IG + TikTok (150.7K-view format from June)
A14: Booth build timelapse | B14: Reel/story | C14: 07:30–09:00 | D14: Stories + report
A15: Fortune draw reactions ×10+ | B15: Short clips | C15: All day | D15: Ad engine (tracker1) + organic
A16: Aloe relief POV ('watch them cool down') | B16: Reel | C16: Peak heat 12–15h | D16: Ads + organic
A17: Lantern corner golden-hour set | B17: Photos + b-roll | C17: 17–18:30 | D17: Brand library + Q3 report
A18: Creator visits + kit unboxings | B18: Creator-owned | C18: Scheduled slots | D18: Whitelist best into Spark/Meta
A19: NYC: bag assembly + FIT drop-off photos | B19: Photos | C19: Sep 9–10 | D19: Recap post + BOD report
A21: POST-EVENT (Sep 13–30)
A22: Action | B22: Detail | C22: Owner | D22: Due
A23: Content offload → calendar | B23: 40–60 clips → 4–6 weeks organic + ad engine | C23: Brand team | D23: Sep 15
A24: Reshare + whitelist UGC | B24: Best tagged posts → stories; top creators → Spark Ads | C24: Brand team | D24: Sep 20
A25: Redemption + email report | B25: glossypop / gameday code redemptions + Klaviyo list growth | C25: Brand Director | D25: Oct 2
A26: Q3 report event section | B26: Reuse May 'growth after the event' framing | C26: Brand Director | D26: Oct
A27: Q4 gifting segue | B27: Voucher validity ends Sep 30 → retarget into Q4 'Thoughtful Gifting' | C27: Brand team | D27: Oct
